robotframework_airtest/__init__.py
robotframework_airtest/airtest/__init__.py
robotframework_airtest/cli/__init__.py
robotframework_airtest/cli/template.py
robotframework_airtest/cli/util.py
robotframework_airtest/cli/vmg.py
robotframework_airtest/device/__init__.py
robotframework_airtest/device/connects/__init__.py
robotframework_airtest/device/connects/connect.py
robotframework_airtest/device/connects/connect_strategy.py
robotframework_airtest/device/connects/impl/__init__.py
robotframework_airtest/device/connects/impl/android.py
robotframework_airtest/device/connects/impl/ios.py
robotframework_airtest/device/connects/impl/unity.py
robotframework_airtest/device/connects/impl/windows.py
robotframework_airtest/dll/openh264-1.8.0-win32.dll
robotframework_airtest/dll/openh264-1.8.0-win64.dll
robotframework_airtest/poco/__init__.py
robotframework_airtest/poco/android.py
robotframework_airtest/poco/base.py
robotframework_airtest/poco/cocosjs.py
robotframework_airtest/poco/gesture.py
robotframework_airtest/poco/ios.py
robotframework_airtest/poco/std.py
robotframework_airtest/poco/ue4.py
robotframework_airtest/poco/unity.py
robotframework_airtest/reporter/__init__.py
robotframework_airtest/template/.vscode/extensions.json
robotframework_airtest/template/.vscode/launch.json
robotframework_airtest/template/.vscode/settings.json
robotframework_airtest/template/.vscode/settings.json.sample
robotframework_airtest/template/.vscode/tasks.json
robotframework_airtest/template/Args/config.py
robotframework_airtest/template/Args/debug.args
robotframework_airtest/template/Args/dryrun.args
robotframework_airtest/template/Args/run.args
robotframework_airtest/template/asset/2023-10-21-05-06-28.png
robotframework_airtest/template/asset/2023-10-21-05-09-16.png
robotframework_airtest/template/asset/2023-10-21-05-09-30.png
robotframework_airtest/template/asset/2023-10-21-05-20-24.png
robotframework_airtest/template/asset/2023-10-21-05-30-41.png
robotframework_airtest/template/Docs/使用说明.md
robotframework_airtest-0.3.1.dist-info/entry_points.txt
robotframework_airtest-0.3.1.dist-info/METADATA
robotframework_airtest-0.3.1.dist-info/WHEEL
robotframework_airtest-0.3.1.dist-info/RECORD
