Metadata-Version: 2.1
Name: robotframework-airtest
Version: 0.3.1
Summary: 网易Airtest/pocoui的Robotframework测试库
Home-page: https://github.com/kaluluosi/robotframework-airtest
License: MIT
Author: kaluluosi
Author-email: kaluluosi@gmail.com
Requires-Python: >=3.8,<=3.9
Classifier: License :: OSI Approved :: MIT License
Classifier: Programming Language :: Python :: 3
Classifier: Programming Language :: Python :: 3.8
Classifier: Programming Language :: Python :: 3.9
Requires-Dist: click (>=8.1.7,<9.0.0)
Requires-Dist: docutils (>=0.20.1,<0.21.0)
Requires-Dist: pocoui (>=1.0.89,<2.0.0)
Requires-Dist: pydantic-settings (>=2.0.3,<3.0.0)
Requires-Dist: pymdown-extensions (>=10.3.1,<11.0.0)
Requires-Dist: robotframework (>=6.1.1,<7.0.0)
Requires-Dist: toml (>=0.10.2,<0.11.0)
Requires-Dist: unityparser (>=3.0.1,<4.0.0)
Project-URL: Repository, https://github.com/kaluluosi/robotframework-airtest
